README.rst
setup.cfg
setup.py
ecsutils.egg-info/PKG-INFO
ecsutils.egg-info/SOURCES.txt
ecsutils.egg-info/dependency_links.txt
ecsutils.egg-info/requires.txt
ecsutils.egg-info/top_level.txt
utils/__init__.py
utils/ecs.py