Metadata-Version: 1.1
Name: ecsutils
Version: 1.0.3
Summary: Ansible Alicloud ecs utils
Home-page: UNKNOWN
Author: xiaozhu
Author-email: heguimin36@163.com
License: MIT
Keywords: sample ecsutils development
Platform: UNKNOWN
Classifier: Development Status :: 3 - Alpha
Classifier: Intended Audience :: Developers
Classifier: Topic :: Software Development :: Build Tools
Classifier: License :: OSI Approved :: MIT License
Classifier: Programming Language :: Python :: 2
Classifier: Programming Language :: Python :: 2.6
Classifier: Programming Language :: Python :: 2.7
